aristonremotethermo/__init__.py
aristonremotethermo/ariston.py
aristonremotethermo-2.0.14.dist-info/LICENSE.txt
aristonremotethermo-2.0.14.dist-info/METADATA
aristonremotethermo-2.0.14.dist-info/WHEEL
aristonremotethermo-2.0.14.dist-info/top_level.txt
aristonremotethermo-2.0.14.dist-info/RECORD
