Metadata-Version: 2.1
Name: aristonremotethermo
Version: 2.0.14
Summary: Ariston NET Remotethermo integration
Home-page: https://github.com/chomupashchuk/ariston-remotethermo-api
Download-URL: https://pypi.org/project/aristonremotethermo/
Author: Oleh Pashchuk
Author-email: chomu.nattsol@gmail.com
License: MIT
Keywords: Ariston NET,Remotethermo,Ariston
License-File: LICENSE.txt
Requires-Dist: requests
